LICENSE
kiwi_tasting/__init__.py
kiwi_tasting/__main__.py
kiwi_tasting/app.py
kiwi_tasting/assets/img/logo.ico
kiwi_tasting/assets/img/openkiwi-logo-horizontal.png
kiwi_tasting/predefined_data.py
pyproject.toml
openkiwi_tasting-0.1.0.dist-info/entry_points.txt
openkiwi_tasting-0.1.0.dist-info/LICENSE
openkiwi_tasting-0.1.0.dist-info/WHEEL
openkiwi_tasting-0.1.0.dist-info/METADATA
openkiwi_tasting-0.1.0.dist-info/RECORD
